CHANGELOG.md
LICENSE.md
README.md
setup.py
pylu/__init__.py
pylu/dgesv.c
pylu/dgesv.pxd
pylu/dgesv.pyx
pylu.egg-info/PKG-INFO
pylu.egg-info/SOURCES.txt
pylu.egg-info/dependency_links.txt
pylu.egg-info/not-zip-safe
pylu.egg-info/requires.txt
pylu.egg-info/top_level.txt
test/pylu_test.py